odoo/addons/l10n_ro_nondeductible_vat/README.rst
odoo/addons/l10n_ro_nondeductible_vat/__init__.py
odoo/addons/l10n_ro_nondeductible_vat/__manifest__.py
odoo/addons/l10n_ro_nondeductible_vat/i18n/l10n_ro_nondeductible_vat.pot
odoo/addons/l10n_ro_nondeductible_vat/i18n/ro.po
odoo/addons/l10n_ro_nondeductible_vat/models/__init__.py
odoo/addons/l10n_ro_nondeductible_vat/models/account_account.py
odoo/addons/l10n_ro_nondeductible_vat/models/account_move.py
odoo/addons/l10n_ro_nondeductible_vat/models/account_move_line.py
odoo/addons/l10n_ro_nondeductible_vat/models/account_partial_reconcile.py
odoo/addons/l10n_ro_nondeductible_vat/models/account_tax.py
odoo/addons/l10n_ro_nondeductible_vat/models/account_tax_repartition_line.py
odoo/addons/l10n_ro_nondeductible_vat/models/stock_move.py
odoo/addons/l10n_ro_nondeductible_vat/models/stock_quant.py
odoo/addons/l10n_ro_nondeductible_vat/readme/CONTRIBUTORS.md
odoo/addons/l10n_ro_nondeductible_vat/readme/DESCRIPTION.md
odoo/addons/l10n_ro_nondeductible_vat/readme/INSTALL.md
odoo/addons/l10n_ro_nondeductible_vat/readme/USAGE.md
odoo/addons/l10n_ro_nondeductible_vat/static/description/icon.png
odoo/addons/l10n_ro_nondeductible_vat/static/description/index.html
odoo/addons/l10n_ro_nondeductible_vat/tests/__init__.py
odoo/addons/l10n_ro_nondeductible_vat/tests/common.py
odoo/addons/l10n_ro_nondeductible_vat/tests/test_consum.py
odoo/addons/l10n_ro_nondeductible_vat/tests/test_inventory.py
odoo/addons/l10n_ro_nondeductible_vat/tests/test_invoice.py
odoo/addons/l10n_ro_nondeductible_vat/views/account_account_view.xml
odoo/addons/l10n_ro_nondeductible_vat/views/account_move_view.xml
odoo/addons/l10n_ro_nondeductible_vat/views/account_tax_view.xml
odoo/addons/l10n_ro_nondeductible_vat/views/stock_picking_view.xml
odoo/addons/l10n_ro_nondeductible_vat/views/stock_quant_view.xml
odoo_addon_l10n_ro_nondeductible_vat-19.0.0.1.0.dist-info/METADATA
odoo_addon_l10n_ro_nondeductible_vat-19.0.0.1.0.dist-info/WHEEL
odoo_addon_l10n_ro_nondeductible_vat-19.0.0.1.0.dist-info/top_level.txt
odoo_addon_l10n_ro_nondeductible_vat-19.0.0.1.0.dist-info/RECORD
